hakxcore/__init__.py
hakxcore/__main__.py
hakxcore-0.0.9.dist-info/LICENCE
hakxcore-0.0.9.dist-info/METADATA
hakxcore-0.0.9.dist-info/WHEEL
hakxcore-0.0.9.dist-info/entry_points.txt
hakxcore-0.0.9.dist-info/top_level.txt
hakxcore-0.0.9.dist-info/RECORD
