Metadata-Version: 2.1
Name: hakxcore
Version: 0.0.9
Summary: Hakxcore personal Repo and python package
Home-page: https://github.com/hakxcore/hakxcore
Author: Mukesh Kumar
Author-email: mukeshkumarchark@gmail.com
License: MIT Licence
Download-URL: https://github.com/hakxcore/hakxcore/archive/refs/heads/main.zip
Keywords: hakxcore,bug bounty,mukesh,pentesting,security,development,enterprenurship
Platform: UNKNOWN
Classifier: Development Status :: 5 - Production/Stable
Classifier: Intended Audience :: Developers
Classifier: Intended Audience :: Information Technology
Classifier: Operating System :: OS Independent
Classifier: Topic :: Security
Classifier: License :: OSI Approved :: MIT License
Classifier: Programming Language :: Python :: 3.4
License-File: LICENCE
Requires-Dist: colorama
Requires-Dist: future
Requires-Dist: terminaltables
